qubed-0.3.0.dist-info/METADATA
qubed-0.3.0.dist-info/WHEEL
qubed-0.3.0.dist-info/entry_points.txt
qubed-0.3.0.dist-info/licenses/LICENSE.txt
qubed.libs/libgcc_s-0366c7ba.so.1
qubed/Qube.py
qubed/__init__.py
qubed/__main__.py
qubed/convert.py
qubed/examples.py
qubed/formatters.py
qubed/metadata.py
qubed/protobuf/__init__.py
qubed/protobuf/adapters.py
qubed/protobuf/qube.proto
qubed/protobuf/qube_pb2.py
qubed/protobuf/qube_pb2.pyi
qubed/py.typed
qubed/rust.cpython-311-arm-linux-musleabihf.so
qubed/selection.py
qubed/serialisation.py
qubed/set_operations.py
qubed/trie.py
qubed/types.py
qubed/value_types.py
qubed-0.3.0.dist-info/RECORD
