Metadata-Version: 2.4
Name: qubed
Version: 0.3.0
Classifier: Programming Language :: Rust
Classifier: Programming Language :: Python :: Implementation :: CPython
Classifier: Programming Language :: Python :: Implementation :: PyPy
Requires-Dist: frozendict
Requires-Dist: numpy>=1.26
Requires-Dist: protobuf
Requires-Dist: requests
Requires-Dist: rich ; extra == 'cli'
Requires-Dist: click ; extra == 'cli'
Requires-Dist: psutil ; extra == 'cli'
Requires-Dist: pyfdb ; extra == 'cli'
Requires-Dist: pyyaml ; extra == 'cli'
Requires-Dist: fastapi[standard] ; extra == 'stac-server'
Requires-Dist: jinja2 ; extra == 'stac-server'
Requires-Dist: sphinx ; extra == 'docs'
Requires-Dist: sphinx-rtd-theme ; extra == 'docs'
Requires-Dist: myst-nb ; extra == 'docs'
Requires-Dist: sphinx-autobuild ; extra == 'docs'
Requires-Dist: jupyterlab ; extra == 'docs'
Requires-Dist: ipykernel ; extra == 'docs'
Requires-Dist: scipy ; extra == 'docs'
Requires-Dist: objsize ; extra == 'docs'
Requires-Dist: humanize ; extra == 'docs'
Requires-Dist: pandas ; extra == 'docs'
Requires-Dist: pytest ; extra == 'dev'
Requires-Dist: black ; extra == 'dev'
Requires-Dist: ruff ; extra == 'dev'
Requires-Dist: flake8 ; extra == 'dev'
Requires-Dist: pre-commit ; extra == 'dev'
Requires-Dist: isort ; extra == 'dev'
Requires-Dist: httpx ; extra == 'dev'
Requires-Dist: cbor2 ; extra == 'cbor'
Provides-Extra: cli
Provides-Extra: stac_server
Provides-Extra: docs
Provides-Extra: dev
Provides-Extra: cbor
License-File: LICENSE.txt
Summary: A library that provides a tree of datacubes called Qube.
Author-email: Tom Hodson <thomas.hodson@ecmwf.int>
Requires-Python: >=3.11
